src/mcp_obsidian/__init__.py
src/mcp_obsidian/obsidian.py
src/mcp_obsidian/server.py
src/mcp_obsidian/tools.py
orange_mcp_obsidian-0.2.1.dist-info/METADATA
orange_mcp_obsidian-0.2.1.dist-info/WHEEL
orange_mcp_obsidian-0.2.1.dist-info/entry_points.txt
orange_mcp_obsidian-0.2.1.dist-info/licenses/LICENSE
orange_mcp_obsidian-0.2.1.dist-info/RECORD
